text_function_by_example/__init__.py
text_function_by_example/__main__.py
text_function_by_example/codegen.py
text_function_by_example/templates/__init__.py
text_function_by_example/templates/failure_prompt.txt
text_function_by_example/templates/prompt.txt
text_function_by_example/templates/wrapper_script.py
text_function_by_example-0.2.0.dist-info/LICENSE
text_function_by_example-0.2.0.dist-info/METADATA
text_function_by_example-0.2.0.dist-info/WHEEL
text_function_by_example-0.2.0.dist-info/top_level.txt
text_function_by_example-0.2.0.dist-info/RECORD
